oneNeuron/__init__.py
oneNeuron/perceptron.py
One_Neuron_pypi_Basavaraj100-0.0.2.dist-info/LICENSE
One_Neuron_pypi_Basavaraj100-0.0.2.dist-info/METADATA
One_Neuron_pypi_Basavaraj100-0.0.2.dist-info/WHEEL
One_Neuron_pypi_Basavaraj100-0.0.2.dist-info/top_level.txt
One_Neuron_pypi_Basavaraj100-0.0.2.dist-info/RECORD
