Metadata-Version: 2.1
Name: One-Neuron-pypi-Basavaraj100
Version: 0.0.2
Summary: its an implimentation of Perceptron
Home-page: https://github.com/Basavaraj100/One_Neuron_pypi
Author: Basavaraj100
Author-email: benkibijali@gmail.com
License: UNKNOWN
Project-URL: Bug Tracker, https://github.com/Basavaraj100/One_Neuron_pypi/issues
Platform: UNKNOWN
Classifier: Programming Language :: Python :: 3
Classifier: License :: OSI Approved :: MIT License
Classifier: Operating System :: OS Independent
Requires-Python: >=3.7
License-File: LICENSE
Requires-Dist: numpy
Requires-Dist: tqdm
